[
  {
    "track": {
      "trackName": "Wagner: Die Walküre, Act 1: Prelude",
      "artistName": "Richard Wagner",
      "albumName": "Wagner: Der Ring des Nibelungen [Bayreuth, 1991 & 1992]",
      "trackUri": "spotify:track:4zb7KcyNNHPboNByognKau"
    },
    "episode": null,
    "audiobook": null,
    "localTrack": null,
    "addedDate": "2016-09-27"
  },
  {
    "track": {
      "trackName": "Küß\" mich, bitte, bitte küß\" mich",
      "artistName": "Adalbert Lutter und sein Tanzorchester",
      "albumName": "German Big Dance Bands, Vol. 9",
      "trackUri": "spotify:track:0LsPxoqY983tUjcYlCy4TP"
    },
    "episode": null,
    "audiobook": null,
    "localTrack": null,
    "addedDate": "2016-09-28"
  },
  {
    "track": {
      "trackName": "Wolf: Mörike-Lieder: No. 12, Verborgenheit",
      "artistName": "Hugo Wolf",
      "albumName": "Wolf: Lieder",
      "trackUri": "spotify:track:0goWIbxcUawFOPu8qsYqxd"
    },
    "episode": null,
    "audiobook": null,
    "localTrack": null,
    "addedDate": "2016-09-27"
  },
  {
    "track": {
      "trackName": "Schubert: Erlkönig, Op. 1, D. 328",
      "artistName": "Franz Schubert",
      "albumName": "21 Leider",
      "trackUri": "spotify:track:0hES7IYAQSwBAPXJeLKcGN"
    },
    "episode": null,
    "audiobook": null,
    "localTrack": null,
    "addedDate": "2016-09-27"
  },
  {
    "track": {
      "trackName": "Winterreise, Op. 89, D. 911: No. 24. Der Leiermann",
      "artistName": "Franz Schubert",
      "albumName": "Schubert: Winterreise, Op. 89, D. 911",
      "trackUri": "spotify:track:1DGqOky0ThGGIG8pZQU3H3"
    },
    "episode": null,
    "audiobook": null,
    "localTrack": null,
    "addedDate": "2016-09-27"
  },
  {
    "track": {
      "trackName": "Les Préludes, symphonic poem No. 3, S.97",
      "artistName": "Franz Liszt",
      "albumName": "Berlioz: Symphonie fantastique/Liszt: Les Préludes",
      "trackUri": "spotify:track:4TdTH6t8P6pky1wTl2SMdM"
    },
    "episode": null,
    "audiobook": null,
    "localTrack": null,
    "addedDate": "2016-09-27"
  },
  {
    "track": {
      "trackName": "Der fliegende Holländer: Act III - \"Steuermann, lass die Wacht!\"",
      "artistName": "Richard Wagner",
      "albumName": "Richard Wagner: Fliegende Hollander (Der) [The Flying Dutchman] [Opera Excerpts] [Konwitschny]",
      "trackUri": "spotify:track:4YPcKJTgzqvG6MLuNpUlq9"
    },
    "episode": null,
    "audiobook": null,
    "localTrack": null,
    "addedDate": "2016-09-27"
  },
  {
    "track": {
      "trackName": "Lohengrin: Vorspiel (Orchester)",
      "artistName": "Richard Wagner",
      "albumName": "Wagner: Lohengrin",
      "trackUri": "spotify:track:2Ty8TNz3tOvIgMyhq4m8xP"
    },
    "episode": null,
    "audiobook": null,
    "localTrack": null,
    "addedDate": "2016-09-27"
  },
  {
    "track": {
      "trackName": "Tango Bolero",
      "artistName": "Juan Llossas und sein Tango-Orchester",
      "albumName": "German Big Dance Bands, Vol. 9",
      "trackUri": "spotify:track:5TNy6N9g4URHib99FgM4gV"
    },
    "episode": null,
    "audiobook": null,
    "localTrack": null,
    "addedDate": "2016-09-28"
  },
  {
    "track": {
      "trackName": "The Flying Dutchman: Overture",
      "artistName": "Richard Wagner",
      "albumName": "Richard Wagner: Fliegende Hollander (Der) [The Flying Dutchman] [Opera Excerpts] [Konwitschny]",
      "trackUri": "spotify:track:0EHeq0JhCRfoWKRoYypmRt"
    },
    "episode": null,
    "audiobook": null,
    "localTrack": null,
    "addedDate": "2016-09-27"
  },
  {
    "track": {
      "trackName": "Grand Caprice on Schubert's \"Der Erlkönig\", Op. 26",
      "artistName": "Heinrich Wilhelm Ernst",
      "albumName": "Violino Solo",
      "trackUri": "spotify:track:6xm5IZBmXCZesPSGsQoCj2"
    },
    "episode": null,
    "audiobook": null,
    "localTrack": null,
    "addedDate": "2016-09-27"
  },
  {
    "track": {
      "trackName": "Königgrätzer-Marsch",
      "artistName": "Berliner Pavillon Orchester",
      "albumName": "Beliebte Märsche",
      "trackUri": "spotify:track:2tPoyCQQCdipUYIAeLnOBa"
    },
    "episode": null,
    "audiobook": null,
    "localTrack": null,
    "addedDate": "2016-09-28"
  },
  {
    "track": {
      "trackName": "Wagner: Die Walküre, Act 3: \"Leb wohl, du kühnes, herrliches Kind!\" (Wotan)",
      "artistName": "Richard Wagner",
      "albumName": "Wagner: Der Ring des Nibelungen [Bayreuth, 1991 & 1992]",
      "trackUri": "spotify:track:29smJm4rAY2R068NJ8lqne"
    },
    "episode": null,
    "audiobook": null,
    "localTrack": null,
    "addedDate": "2016-09-27"
  },
  {
    "track": {
      "trackName": "Wagner: Die Walküre, Act 3: \"Der Augen leuchtendes Paar\" (Wotan)",
      "artistName": "Richard Wagner",
      "albumName": "Wagner: Der Ring des Nibelungen [Bayreuth, 1991 & 1992]",
      "trackUri": "spotify:track:1HJjXWCufXJ2nyhM2VW6Rf"
    },
    "episode": null,
    "audiobook": null,
    "localTrack": null,
    "addedDate": "2016-09-27"
  },
  {
    "track": {
      "trackName": "Wagner: Die Walküre, Act 3: \"Loge, hör! Lausche hieher!\" (Wotan)",
      "artistName": "Richard Wagner",
      "albumName": "Wagner: Der Ring des Nibelungen [Bayreuth, 1991 & 1992]",
      "trackUri": "spotify:track:3mu3EAGPmr44QNyFx8NhOX"
    },
    "episode": null,
    "audiobook": null,
    "localTrack": null,
    "addedDate": "2016-09-27"
  },
  {
    "track": {
      "trackName": "Wagner: Siegfried, Act 2: Prelude",
      "artistName": "Richard Wagner",
      "albumName": "Wagner: Der Ring des Nibelungen [Bayreuth, 1991 & 1992]",
      "trackUri": "spotify:track:6IPCm81wQXpSjtppDEJGhn"
    },
    "episode": null,
    "audiobook": null,
    "localTrack": null,
    "addedDate": "2016-09-27"
  },
  {
    "track": {
      "trackName": "Wagner: Siegfried, Act 3: Prelude",
      "artistName": "Richard Wagner",
      "albumName": "Wagner: Der Ring des Nibelungen [Bayreuth, 1991 & 1992]",
      "trackUri": "spotify:track:08HoWGNkvOQBTMH4SlUqWX"
    },
    "episode": null,
    "audiobook": null,
    "localTrack": null,
    "addedDate": "2016-09-27"
  },
  {
    "track": {
      "trackName": "19 Hungarian Rhapsodies, S244/R106: No. 15 in A Minor, \"Rakoczy March\"",
      "artistName": "Franz Liszt",
      "albumName": "Liszt: Hungarian Rhapsodies for Piano (Complete)",
      "trackUri": "spotify:track:4B2ykUNAPnPI9JT4bqbmKY"
    },
    "episode": null,
    "audiobook": null,
    "localTrack": null,
    "addedDate": "2016-09-28"
  },
  {
    "track": {
      "trackName": "A Faust Symphony, S. 108: I. Faust",
      "artistName": "Franz Liszt",
      "albumName": "Liszt: Faust Symphony; Dante Symphony; Les Prélludes; Prometheus",
      "trackUri": "spotify:track:6E8bE0cepuzZsLQO4fOkAs"
    },
    "episode": null,
    "audiobook": null,
    "localTrack": null,
    "addedDate": "2016-09-27"
  },
  {
    "track": {
      "trackName": "Requiem in D Minor, K. 626 : 3. Sequentia: Lacrimosa",
      "artistName": "Wolfgang Amadeus Mozart",
      "albumName": "The Greatest Classical Composers of Germany",
      "trackUri": "spotify:track:3lDicJWgzOgp0APw6Wh3uu"
    },
    "episode": null,
    "audiobook": null,
    "localTrack": null,
    "addedDate": "2016-09-28"
  },
  {
    "track": {
      "trackName": "Hungarian Dance No. 5 in G Minor for Violin and Piano",
      "artistName": "Johannes Brahms",
      "albumName": "The Greatest Classical Composers of Germany",
      "trackUri": "spotify:track:0FkwTKqaZErSvpyBwj9VZj"
    },
    "episode": null,
    "audiobook": null,
    "localTrack": null,
    "addedDate": "2016-09-28"
  },
  {
    "track": {
      "trackName": "Carmina Burana: \"O Fortuna\"",
      "artistName": "Carl Orff",
      "albumName": "The Greatest Classical Composers of Germany",
      "trackUri": "spotify:track:2S2ZCttPdBMEVsh8CgVJIk"
    },
    "episode": null,
    "audiobook": null,
    "localTrack": null,
    "addedDate": "2016-09-28"
  },
  {
    "track": {
      "trackName": "Sixteen Waltzes, Op. 39: No. 9 in D Minor",
      "artistName": "Johannes Brahms",
      "albumName": "The Greatest Classical Composers of Germany",
      "trackUri": "spotify:track:07GiQIDUNUGEEnZ9pgJtjM"
    },
    "episode": null,
    "audiobook": null,
    "localTrack": null,
    "addedDate": "2016-09-28"
  },
  {
    "track": {
      "trackName": "Old, Oie",
      "artistName": "Alfred Hause und sein Orchester",
      "albumName": "German Big Dance Bands, Vol. 9",
      "trackUri": "spotify:track:7sCrOr9YK73hrb9DKlgBRX"
    },
    "episode": null,
    "audiobook": null,
    "localTrack": null,
    "addedDate": "2016-09-28"
  },
  {
    "track": {
      "trackName": "Götterdämmerung, WWV 86D: Act III: Trauermarsch (Siegfried's Funeral March)",
      "artistName": "Richard Wagner",
      "albumName": "Wagner: Götterdämmerung",
      "trackUri": "spotify:track:4OTyLVGtIUTdgLUQBSPmwz"
    },
    "episode": null,
    "audiobook": null,
    "localTrack": null,
    "addedDate": "2016-09-28"
  },
  {
    "track": {
      "trackName": "Symphony No. 3: Ig. Im alten Marschtempo. Allegro moderato",
      "artistName": "Gustav Mahler",
      "albumName": "Gustav Mahler: Symphony No. 3",
      "trackUri": "spotify:track:2inP4wDWTitEjzIKdZWST8"
    },
    "episode": null,
    "audiobook": null,
    "localTrack": null,
    "addedDate": "2016-10-06"
  },
  {
    "track": {
      "trackName": "It's a Hep, Hap, Happy Day",
      "artistName": "Teddy Stauffer und seine Original Teddies",
      "albumName": "German Big Dance Bands, Vol. 9",
      "trackUri": "spotify:track:0bkfL3whMUOLlf8F6NxFfM"
    },
    "episode": null,
    "audiobook": null,
    "localTrack": null,
    "addedDate": "2016-10-10"
  },
  {
    "track": {
      "trackName": "Brahms: 21 Hungarian Dances, WoO 1: No. 1 in G Minor (Arr. Joachim for Violin and PIano)",
      "artistName": "Johannes Brahms",
      "albumName": "Brahms: Violin Sonatas Nos. 1-3 & 4 Hungarian Dances",
      "trackUri": "spotify:track:0H9J5CU0xXqeuSfJNZRbBl"
    },
    "episode": null,
    "audiobook": null,
    "localTrack": null,
    "addedDate": "2016-10-19"
  },
  {
    "track": {
      "trackName": "Brahms: Violin Sonata No. 1 in G Major, Op. 78: I. Vivace, ma non troppo",
      "artistName": "Johannes Brahms",
      "albumName": "Brahms: Violin Sonatas Nos. 1-3 & 4 Hungarian Dances",
      "trackUri": "spotify:track:3OYnO2GLaJmRuXaOEQHnp5"
    },
    "episode": null,
    "audiobook": null,
    "localTrack": null,
    "addedDate": "2016-10-19"
  },
  {
    "track": {
      "trackName": "Brahms: Violin Sonata No. 3 in D Minor, Op. 108: I. Allegro",
      "artistName": "Johannes Brahms",
      "albumName": "Brahms: Violin Sonatas Nos. 1-3 & 4 Hungarian Dances",
      "trackUri": "spotify:track:6eF2ezWE3F03YiNnwgW3lo"
    },
    "episode": null,
    "audiobook": null,
    "localTrack": null,
    "addedDate": "2016-10-19"
  },
  {
    "track": {
      "trackName": "Verschwiegene Liebe - Voice",
      "artistName": "Hugo Wolf",
      "albumName": "Classical Barbra (Re-Mastered)",
      "trackUri": "spotify:track:3EfuBPHchiS5PIepoWmIrC"
    },
    "episode": null,
    "audiobook": null,
    "localTrack": null,
    "addedDate": "2016-11-30"
  },
  {
    "track": {
      "trackName": "Faust Overture",
      "artistName": "Richard Wagner",
      "albumName": "Wagner : The Classics",
      "trackUri": "spotify:track:5tw9pNtT29bjgn5f9JIXM7"
    },
    "episode": null,
    "audiobook": null,
    "localTrack": null,
    "addedDate": "2016-12-07"
  },
  {
    "track": {
      "trackName": "Piano Concerto No. 21 in C Major, K. 467: II. Andante",
      "artistName": "Wolfgang Amadeus Mozart",
      "albumName": "Mozart, W.A.: Eine kleine Nachtmusik",
      "trackUri": "spotify:track:6knDf2Q8lt3NATku6uSrx6"
    },
    "episode": null,
    "audiobook": null,
    "localTrack": null,
    "addedDate": "2017-02-27"
  },
  {
    "track": {
      "trackName": "21 Hungarian Dances, WoO 1: No. 5 in G Minor (Orch. Schmeling)",
      "artistName": "Johannes Brahms",
      "albumName": "50 Classical Masterworks",
      "trackUri": "spotify:track:53qnPrS9ZwqcbwIAbJqFsl"
    },
    "episode": null,
    "audiobook": null,
    "localTrack": null,
    "addedDate": "2017-02-27"
  },
  {
    "track": {
      "trackName": "Liebestraum No.3 In A-Flat Major, S.541 No.3: Notturno III: O lieb, so lang du lieben kannst",
      "artistName": "Franz Liszt",
      "albumName": "Liszt - Wild and Crazy",
      "trackUri": "spotify:track:5qpUmfrVRpCrzjQXeouFVa"
    },
    "episode": null,
    "audiobook": null,
    "localTrack": null,
    "addedDate": "2017-02-27"
  },
  {
    "track": {
      "trackName": "Liebestraume, S541/R211 : No. 3: Nocturne in A-Flat Major",
      "artistName": "Franz Liszt",
      "albumName": "Liszt: Scherzo and March / 3 Liebestraume / Berceuse",
      "trackUri": "spotify:track:6GzMz3s0K1YKwRVI36CgRx"
    },
    "episode": null,
    "audiobook": null,
    "localTrack": null,
    "addedDate": "2018-02-15"
  },
  {
    "track": {
      "trackName": "En rêve, S. 207",
      "artistName": "Franz Liszt",
      "albumName": "Liszt: Sonata in B Minor - Piano Works",
      "trackUri": "spotify:track:0eiT0cfG4TT3u6Zw68A1Kw"
    },
    "episode": null,
    "audiobook": null,
    "localTrack": null,
    "addedDate": "2018-02-15"
  },
  {
    "track": {
      "trackName": "Ständchen (From Schwanengesang, D957)",
      "artistName": "Franz Liszt",
      "albumName": "Kissin Plays Liszt",
      "trackUri": "spotify:track:1Fye8VOMOlXxtBo02TpNWD"
    },
    "episode": null,
    "audiobook": null,
    "localTrack": null,
    "addedDate": "2018-02-15"
  },
  {
    "track": {
      "trackName": "Les Jeux d'eaux a la Villa d'Este, S. 163",
      "artistName": "Franz Liszt",
      "albumName": "Franz Liszt: Volume 2",
      "trackUri": "spotify:track:0Pzp03HQh9ZKE6pdSj9E5O"
    },
    "episode": null,
    "audiobook": null,
    "localTrack": null,
    "addedDate": "2018-02-15"
  },
  {
    "track": {
      "trackName": "3 Études de Concert, S. 144: No. 3 in D-Flat Major \"Un sospiro\"",
      "artistName": "Franz Liszt",
      "albumName": "Liszt: The Essentials",
      "trackUri": "spotify:track:2KP5jrHQqBFPal7qPqh9qs"
    },
    "episode": null,
    "audiobook": null,
    "localTrack": null,
    "addedDate": "2018-02-15"
  },
  {
    "track": {
      "trackName": "Grandes Études de Paganini, S. 141: No. 3 in G-Sharp Minor \"La Campanella\"",
      "artistName": "Franz Liszt",
      "albumName": "Liszt: The Essentials",
      "trackUri": "spotify:track:4TahqzA00VSYl5IE8mOGSv"
    },
    "episode": null,
    "audiobook": null,
    "localTrack": null,
    "addedDate": "2018-02-15"
  },
  {
    "track": {
      "trackName": "Roman nepi tancok (Romanian Folk Dances), BB 68: Six Romanian Folkdances, Sz. 56",
      "artistName": "Béla Bartók",
      "albumName": "Bartok (The Best Of)",
      "trackUri": "spotify:track:0LUyqZFTd32wJsTpUcaBEc"
    },
    "episode": null,
    "audiobook": null,
    "localTrack": null,
    "addedDate": "2018-02-15"
  },
  {
    "track": {
      "trackName": "Romanian Folk Dances for Orchestra, Sz. 68 (Transcr. Willner for String Orchestra)",
      "artistName": "Béla Bartók",
      "albumName": "Lutosławski: Musique funèbre - Bartók: Divertimento; Choruses",
      "trackUri": "spotify:track:06gaSZpTxkLgZ7gZVlXCw3"
    },
    "episode": null,
    "audiobook": null,
    "localTrack": null,
    "addedDate": "2018-02-15"
  },
  {
    "track": {
      "trackName": "Concerto for Orchestra, Sz. 116: III. Elegia. Andante non troppo",
      "artistName": "Béla Bartók",
      "albumName": "Bartók: Concerto for Orchestra & Piano Concerto No. 3",
      "trackUri": "spotify:track:5Lt149p3CN0MocBC4rzErj"
    },
    "episode": null,
    "audiobook": null,
    "localTrack": null,
    "addedDate": "2018-02-15"
  },
  {
    "track": {
      "trackName": "String Quartet No. 2, Sz. 67: II. Allegro molto capriccioso",
      "artistName": "Béla Bartók",
      "albumName": "Bartok: Complete String Quartets",
      "trackUri": "spotify:track:5Gyd42kIry0E8izR81Tr06"
    },
    "episode": null,
    "audiobook": null,
    "localTrack": null,
    "addedDate": "2018-02-15"
  },
  {
    "track": {
      "trackName": "Piano Concerto in E-Flat Major, Op. 31: III. Ausserst ruhig, versonnen, schwarmerisch",
      "artistName": "Hans Pfitzner",
      "albumName": "Staatskapelle Dresden Edition, Vol. 34",
      "trackUri": "spotify:track:1EgeCZO2VMuLEJtBfXUqpI"
    },
    "episode": null,
    "audiobook": null,
    "localTrack": null,
    "addedDate": "2018-02-15"
  },
  {
    "track": {
      "trackName": "Palestrina - Musical Legend In Three Acts: Prelude to Act I. Ruhig (Andante)",
      "artistName": "Hans Pfitzner",
      "albumName": "Pfitzner: Palestrina",
      "trackUri": "spotify:track:2V7hkr9zndVJ08f2LtLfhg"
    },
    "episode": null,
    "audiobook": null,
    "localTrack": null,
    "addedDate": "2018-02-15"
  },
  {
    "track": {
      "trackName": "Die Rose vom Liebesgarten, Act I: Waldes Rauschen weit und wogend",
      "artistName": "Hans Pfitzner",
      "albumName": "Pfitzner: Die Rose vom Liebesgarten",
      "trackUri": "spotify:track:3DJgBYDvdwrtVcjSWxz0sI"
    },
    "episode": null,
    "audiobook": null,
    "localTrack": null,
    "addedDate": "2018-02-15"
  },
  {
    "track": {
      "trackName": "Mephisto Waltz No. 1, S. 514",
      "artistName": "Franz Liszt",
      "albumName": "Kissin Plays Liszt",
      "trackUri": "spotify:track:0h4Yg2192HQ8jHEcGj2Piy"
    },
    "episode": null,
    "audiobook": null,
    "localTrack": null,
    "addedDate": "2018-04-01"
  },
  {
    "track": {
      "trackName": "Wagner: Das Rheingold: Prelude",
      "artistName": "Richard Wagner",
      "albumName": "Wagner: Der Ring des Nibelungen [Bayreuth, 1991 & 1992]",
      "trackUri": "spotify:track:2ey9F0tRODlFnXJgyNcXr0"
    },
    "episode": null,
    "audiobook": null,
    "localTrack": null,
    "addedDate": "2019-06-27"
  },
  {
    "track": {
      "trackName": "Wagner: Das Rheingold: \"Weia! Waga! Woge du Welle!\" (Woglinde, Wellgunde, Flosshilde)",
      "artistName": "Richard Wagner",
      "albumName": "Wagner: Der Ring des Nibelungen [Bayreuth, 1991 & 1992]",
      "trackUri": "spotify:track:37RqMfgLu70pwZdVYLb1O0"
    },
    "episode": null,
    "audiobook": null,
    "localTrack": null,
    "addedDate": "2019-06-27"
  },
  {
    "track": {
      "trackName": "Wagner: Das Rheingold: \"He he! Ihr Nicker!\" (Alberich, Woglinde, Wellgunde, Flosshilde)",
      "artistName": "Richard Wagner",
      "albumName": "Wagner: Der Ring des Nibelungen [Bayreuth, 1991 & 1992]",
      "trackUri": "spotify:track:0DgJ1KTPHIKiTD0XSfmExO"
    },
    "episode": null,
    "audiobook": null,
    "localTrack": null,
    "addedDate": "2019-06-27"
  },
  {
    "track": {
      "trackName": "Prussia’s Glory - The Glory Of Prussia - Preussens Gloria",
      "artistName": "Mountain Division Light Infantry",
      "albumName": "Grand Tatoo . Military Marches - Marches Militaires",
      "trackUri": "spotify:track:0toF6vZjONW8ge8c4qPCZg"
    },
    "episode": null,
    "audiobook": null,
    "localTrack": null,
    "addedDate": "2024-11-21"
  },
  {
    "track": {
      "trackName": "Königgrätzer Marsch",
      "artistName": "Die Marschmusikanten",
      "albumName": "Schätze der Marschmusik",
      "trackUri": "spotify:track:0C10DHSTlXHswocILTXLbO"
    },
    "episode": null,
    "audiobook": null,
    "localTrack": null,
    "addedDate": "2024-11-21"
  },
  {
    "track": {
      "trackName": "Auf der Heide blüht ein kleines Blümelein",
      "artistName": "Chor des Kameradschaftsbundes Frankfurt und großes Blasorchester",
      "albumName": "Die schönsten Märsche, Vol. 4",
      "trackUri": "spotify:track:6SwNvjviZ0eqoQNRCDBflR"
    },
    "episode": null,
    "audiobook": null,
    "localTrack": null,
    "addedDate": "2024-11-21"
  },
  {
    "track": {
      "trackName": "Erika (German Soldier's Song)",
      "artistName": "German Folk Regiment",
      "albumName": "Erika (German Soldier's Song)",
      "trackUri": "spotify:track:6iUVUzg0c2O0KJjxdOvrdr"
    },
    "episode": null,
    "audiobook": null,
    "localTrack": null,
    "addedDate": "2024-11-21"
  }
]